README.txt
setup.py
wsdl2interface.py
wsdl2interface.egg-info/PKG-INFO
wsdl2interface.egg-info/SOURCES.txt
wsdl2interface.egg-info/dependency_links.txt
wsdl2interface.egg-info/entry_points.txt
wsdl2interface.egg-info/requires.txt
wsdl2interface.egg-info/top_level.txt