Metadata-Version: 1.0
Name: wsdl2interface
Version: 1.0b1
Summary: Create zope.interface style interfaces from a WSDL file
Home-page: http://pypi.python.org/pypi/wsdl2interface
Author: Martin Aspeli
Author-email: optilude@gmail.com
License: ZPL
Platform: UNKNOWN
